{
  "1000000": [{
    "id": 1000001,
    "name": "海钓黄翅鱼",
    "brief": "营养丰富，孕妇必选",
    "picUrl": "http://yanxuan.nosdn.127.net/8a9ee5ba08929cc9e40b973607d2f633.png",
    "isNew": false,
    "isHot": true,
    "counterPrice": "",
    "retailPrice": "70.00-73.00"
  }, {
    "id": 1000002,
    "name": "海钓海鲈鱼",
    "brief": "补肾益脾，孕妇必选",
    "picUrl": "http://yanxuan.nosdn.127.net/8a9ee5ba08929cc9e40b973607d2f633.png",
    "isNew": false,
    "isHot": true,
    "counterPrice": "",
    "retailPrice": "50.00-60.00"
  }, {
    "id": 1000003,
    "name": "带鱼",
    "brief": "好吃不贵，富含DHA和EPA",
    "picUrl": "http://yanxuan.nosdn.127.net/8a9ee5ba08929cc9e40b973607d2f633.png",
    "isNew": false,
    "isHot": false,
    "counterPrice": "",
    "retailPrice": "30.00"
  }, {
    "id": 1000004,
    "name": "黄花鱼",
    "brief": "当季海鲜，肉质鲜嫩",
    "picUrl": "http://yanxuan.nosdn.127.net/8a9ee5ba08929cc9e40b973607d2f633.png",
    "isNew": false,
    "isHot": true,
    "counterPrice": "",
    "retailPrice": "37.00-255.00"
  }, {
    "id": 1000005,
    "name": "石斑鱼",
    "brief": "当季海鲜，肉质鲜嫩",
    "picUrl": "http://yanxuan.nosdn.127.net/8a9ee5ba08929cc9e40b973607d2f633.png",
    "isNew": false,
    "isHot": false,
    "counterPrice": "",
    "retailPrice": "60.00"
  }, {
    "id": 1000006,
    "name": "海钓黑鲷",
    "brief": "口感软嫩，富含不饱和脂肪酸",
    "picUrl": "http://yanxuan.nosdn.127.net/8a9ee5ba08929cc9e40b973607d2f633.png",
    "isNew": false,
    "isHot": false,
    "counterPrice": "",
    "retailPrice": "45.00"
  }, {
    "id": 1000007,
    "name": "龙利鱼",
    "brief": "肉质鲜嫩，护眼神鱼",
    "picUrl": "http://yanxuan.nosdn.127.net/8a9ee5ba08929cc9e40b973607d2f633.png",
    "isNew": false,
    "isHot": false,
    "counterPrice": "",
    "retailPrice": "60.00-65.00"
  }, {
    "id": 1000008,
    "name": "银鱼",
    "brief": "高蛋白、低脂肪，补钙首选",
    "picUrl": "http://yanxuan.nosdn.127.net/8a9ee5ba08929cc9e40b973607d2f633.png",
    "isNew": false,
    "isHot": false,
    "counterPrice": "",
    "retailPrice": "17.00"
  }, {
    "id": 1000009,
    "name": "金昌鱼",
    "brief": "好吃不贵，益气养血、柔筋利骨",
    "picUrl": "http://yanxuan.nosdn.127.net/8a9ee5ba08929cc9e40b973607d2f633.png",
    "isNew": false,
    "isHot": false,
    "counterPrice": "",
    "retailPrice": "30.00"
  }, {
    "id": 1000010,
    "name": "巴浪鱼",
    "brief": "营养丰富，具有抗癌作用，因为小，所以污染也少",
    "picUrl": "http://yanxuan.nosdn.127.net/8a9ee5ba08929cc9e40b973607d2f633.png",
    "isNew": false,
    "isHot": false,
    "counterPrice": "",
    "retailPrice": "15.00"
  }],
  "2000000": [{
    "id": 2000001,
    "name": "樱花虾",
    "brief": "口感软嫩，富含不饱和脂肪酸",
    "picUrl": "http://yanxuan.nosdn.127.net/8a9ee5ba08929cc9e40b973607d2f633.png",
    "isNew": false,
    "isHot": true,
    "counterPrice": "",
    "retailPrice": "25.00"
  }, {
    "id": 2000002,
    "name": "草虾(黑虎虾)",
    "brief": "富含虾青素，肉质弹牙",
    "picUrl": "http://yanxuan.nosdn.127.net/8a9ee5ba08929cc9e40b973607d2f633.png",
    "isNew": false,
    "isHot": false,
    "counterPrice": "",
    "retailPrice": "27.00"
  }, {
    "id": 2000003,
    "name": "小斑节虾",
    "brief": "营养丰富，富含虾青素",
    "picUrl": "http://yanxuan.nosdn.127.net/8a9ee5ba08929cc9e40b973607d2f633.png",
    "isNew": false,
    "isHot": true,
    "counterPrice": "",
    "retailPrice": "40.00"
  }],
  "3000000": [{
    "id": 3000001,
    "name": "红鲟(锯缘青蟹)",
    "brief": "营养丰富，含有多种单不饱和与多不饱和脂肪酸",
    "picUrl": "http://yanxuan.nosdn.127.net/8a9ee5ba08929cc9e40b973607d2f633.png",
    "isNew": false,
    "isHot": false,
    "counterPrice": "",
    "retailPrice": "140.00-180.00"
  }, {
    "id": 3000002,
    "name": "扁蟹",
    "brief": "好吃不贵，肉多可口",
    "picUrl": "http://yanxuan.nosdn.127.net/8a9ee5ba08929cc9e40b973607d2f633.png",
    "isNew": false,
    "isHot": false,
    "counterPrice": "",
    "retailPrice": "30.00"
  }, {
    "id": 3000003,
    "name": "螃蟹(3斤装)",
    "brief": "老少皆宜，蛋白质含量超高",
    "picUrl": "http://yanxuan.nosdn.127.net/8a9ee5ba08929cc9e40b973607d2f633.png",
    "isNew": false,
    "isHot": false,
    "counterPrice": "",
    "retailPrice": "235.00"
  }, {
    "id": 3000004,
    "name": "蟹脚肉",
    "brief": "容易烹饪, 营养丰富",
    "picUrl": "http://yanxuan.nosdn.127.net/8a9ee5ba08929cc9e40b973607d2f633.png",
    "isNew": false,
    "isHot": true,
    "counterPrice": "",
    "retailPrice": "30.00"
  }],
  "4000000": [{
    "id": 4000001,
    "name": "鱿鱼",
    "brief": "东山特色，又名叫做小管，肉质Q弹",
    "picUrl": "http://yanxuan.nosdn.127.net/8a9ee5ba08929cc9e40b973607d2f633.png",
    "isNew": false,
    "isHot": true,
    "counterPrice": "",
    "retailPrice": "42.00-47.00"
  }, {
    "id": 4000002,
    "name": "章鱼",
    "brief": "当季海鲜，富含牛磺酸",
    "picUrl": "http://yanxuan.nosdn.127.net/8a9ee5ba08929cc9e40b973607d2f633.png",
    "isNew": false,
    "isHot": false,
    "counterPrice": "",
    "retailPrice": "30.00"
  }],
  "5000000": [{
    "id": 5000001,
    "name": "鲍鱼",
    "brief": "胶原蛋白丰富，美白佳品",
    "picUrl": "http://yanxuan.nosdn.127.net/8a9ee5ba08929cc9e40b973607d2f633.png",
    "isNew": false,
    "isHot": false,
    "counterPrice": "",
    "retailPrice": "37.00-60.00"
  }, {
    "id": 5000002,
    "name": "扇贝",
    "brief": "具有降低血清胆固醇作用，口感滑嫩",
    "picUrl": "http://yanxuan.nosdn.127.net/8a9ee5ba08929cc9e40b973607d2f633.png",
    "isNew": false,
    "isHot": false,
    "counterPrice": "",
    "retailPrice": "19.00-24.00"
  }],
  "6000000": [{
    "id": 6000001,
    "name": "虾干",
    "brief": "补钙首选，孩子孕妇首选",
    "picUrl": "http://yanxuan.nosdn.127.net/8a9ee5ba08929cc9e40b973607d2f633.png",
    "isNew": false,
    "isHot": false,
    "counterPrice": "",
    "retailPrice": "70.00-90.00"
  }, {
    "id": 6000002,
    "name": "鱿鱼母干",
    "brief": "自然烘干，保留最初新鲜风味",
    "picUrl": "http://yanxuan.nosdn.127.net/8a9ee5ba08929cc9e40b973607d2f633.png",
    "isNew": false,
    "isHot": false,
    "counterPrice": "",
    "retailPrice": "100.00"
  }],
  "7000000": []
}
